[
  {
    "keyword": "путешествие",
    "synonyms": [
      "экспедиция",
      "поход"
    ],
    "partial": [
      "плавание"
    ],
    "association": [
      "путешественник"
    ]
  },
  {
    "keyword": "остров",
    "synonyms": [
      "суша",
      "островок"
    ],
    "partial": [
      "атолл",
      "шхера"
    ],
    "association": [
      "архипелаг"
    ]
  },
  {
    "keyword": "город",
    "synonyms": [
      "поселение",
      "поход"
    ],
    "partial": [
      "столица"
    ],
    "association": [
      "горожане",
      "население"
    ]
  },
  {
    "keyword": "корабль",
    "synonyms": [
      "судно"
    ],
    "partial": [
      "парусник",
      "корвет",
      "фрегат"
    ],
    "association": [
      "борт",
      "корма",
      "мачта",
      "нос",
      "парус",
      "кораблестроение"
    ]
  },
  {
    "keyword": "губернатор",
    "synonyms": [
      "правитель",
      "управляющий"
    ],
    "partial": [
    ],
    "association": [
      "губернаторский",
      "губерния"
    ]
  },
  {
    "keyword": "испания",
    "synonyms": [
    ],
    "partial": [
    ],
    "association": [
      "инспаснский",
      "испанцы"
    ]
  },
  {
    "keyword": "гора",
    "synonyms": [
      "вершина",
      "гора",
      "холм",
      "высота"
    ],
    "partial": [
      "сопка",
      "вулкан"
    ],
    "association": [
      "горный",
      "гористый",
      "скала",
      "возвышенность"
    ]
  },
  {
    "keyword": "река",
    "synonyms": [
      "поток"
    ],
    "partial": [
      "ручей"
    ],
    "association": [
      "речка",
      "речной",
      "водоем",
      "течь"
    ]
  },
  {
    "keyword": "король",
    "synonyms": [
      "монарх",
      "правитель"
    ],
    "partial": [
    ],
    "association": [
      "королевский",
      "королева",
      "королевство"
    ]
  },
  {
    "keyword": "восхождение",
    "synonyms": [
      "подъём"
    ],
    "partial": [
    ],
    "association": [
      "взбираться",
      "корабкаться",
      "подниматься"
    ]
  },
  {
    "keyword": "индеец",
    "synonyms": [
      "подъём",
      "краснокожий"
    ],
    "partial": [
    ],
    "association": [
      "индейский",
      "племя",
      "америка"
    ]
  },
  {
    "keyword": "путь",
    "synonyms": [
      "дорога",
      "маршрут"
    ],
    "partial": [
    ],
    "association": [
      "направление",
      "курс",
      "путешествие"
    ]
  },
  {
    "keyword": "берег",
    "synonyms": [
      "побережье",
      "суша"
    ],
    "partial": [
    ],
    "association": [
      "береговой",
      "прибрежный",
      "путешествие"
    ]
  },
  {
    "keyword": "конкистадор",
    "synonyms": [
    ],
    "partial": [
      "завоеватель"
    ],
    "association": [
      "конкистадорский",
      "испания"
    ]
  },
  {
    "keyword": "америка",
    "synonyms": [
    ],
    "partial": [
    ],
    "association": [
      "американский",
      "колумб"
    ]
  },
  {
    "keyword": "море",
    "synonyms": [
    ],
    "partial": [
      "вода"
    ],
    "association": [
      "морской",
      "океан",
      "мореплаватель",
      "мореходство"
    ]
  },
  {
    "keyword": "исследование",
    "synonyms": [
      "экспедиция",
      "разведка"
    ],
    "partial": [
      "вода"
    ],
    "association": [
      "разведывать",
      "исследовать",
      "исследовательский",
      "исследователь"
    ]
  },
  {
    "keyword": "отряд",
    "synonyms": [
      "экипаж",
      "команда"
    ],
    "partial": [
      "моряк",
      "исследователь",
      "мореход"
    ],
    "association": [
    ]
  },
  {
    "keyword": "завоевание",
    "synonyms": [
      "экипаж",
      "команда"
    ],
    "partial": [
      "исследователь",
      "захват",
      "покорение"
    ],
    "association": [
      "война",
      "завоеватель",
      "завоеваткльский"
    ]
  },
  {
    "keyword": "территория",
    "synonyms": [
      "земля",
      "государство"
    ],
    "partial": [
      "граница"
    ],
    "association": [
      "владение"
    ]
  },
  {
    "keyword": "португалия",
    "synonyms": [
    ],
    "partial": [
    ],
    "association": [
      "поргтугалький",
      "Лиссабон"
    ]
  },
  {
    "keyword": "капитан",
    "synonyms": [
      "моряк",
      "мореплаватель"
    ],
    "partial": [
    ],
    "association": [
      "капитанский",
      "корабль",
      "экипаж"
    ]
  },
  {
    "keyword": "альпинист",
    "synonyms": [
      "исследователь"
    ],
    "partial": [
    ],
    "association": [
      "взбираться",
      "гора",
      "альпинизм"
    ]
  },
  {
    "keyword": "британия",
    "synonyms": [
      "великобритания",
      "англия"
    ],
    "partial": [
    ],
    "association": [
      "британский",
      "английский"
    ]
  },
  {
    "keyword": "история",
    "synonyms": [
      "летопись",
      "прошлое"
    ],
    "partial": [
    ],
    "association": [
      "исторический",
      "историк"
    ]
  },
  {
    "keyword": "залив",
    "synonyms": [
    ],
    "partial": [
      "бухта",
      "гавань"
    ],
    "association": [
    ]
  },
  {
    "keyword": "открытие",
    "synonyms": [
      "исследование"
    ],
    "partial": [
      "путешествие"
    ],
    "association": [
      "открыватель",
      "первоткрыватель",
      "открыть"
    ]
  },
  {
    "keyword": "джомолунгма",
    "synonyms": [
      "эверест"
    ],
    "partial": [
    ],
    "association": [
    ]
  },
  {
    "keyword": "африка",
    "synonyms": [
    ],
    "partial": [
    ],
    "association": [
      "африканский",
      "африканец"
    ]
  },
  {
    "keyword": "география",
    "synonyms": [
      "землеописание"
    ],
    "partial": [
    ],
    "association": [
      "географический"
    ]
  },
  {
    "keyword": "исследователь",
    "synonyms": [
      "путешественник"
    ],
    "partial": [
      "мореплаватель"
    ],
    "association": [
      "путешествие",
      "исследование"
    ]
  }
]

